shap_based_tomaster.pypy310-pp73-darwin.so
auto_cluster.pypy310-pp73-darwin.so
utils.pypy310-pp73-darwin.so
shap_based_kmeans.pypy310-pp73-darwin.so
shap_based_hdbscan.pypy310-pp73-darwin.so
antakia_ac-0.2.14.dist-info/RECORD
antakia_ac-0.2.14.dist-info/WHEEL
antakia_ac-0.2.14.dist-info/top_level.txt
antakia_ac-0.2.14.dist-info/METADATA
