Metadata-Version: 2.1
Name: antakia-ac
Version: 0.2.14
Summary: UNKNOWN
Home-page: UNKNOWN
License: UNKNOWN
Platform: UNKNOWN
Requires-Dist: numba
Requires-Dist: scipy
Requires-Dist: scikit-learn
Requires-Dist: tomaster
Requires-Dist: antakia-core
Requires-Dist: importlib-metadata ; python_version >= "3.10"
